README.md
setup.py
phd_utils/__init__.py
phd_utils/files.py
phd_utils/geometry.py
phd_utils/io.py
phd_utils.egg-info/PKG-INFO
phd_utils.egg-info/SOURCES.txt
phd_utils.egg-info/dependency_links.txt
phd_utils.egg-info/requires.txt
phd_utils.egg-info/top_level.txt