Metadata-Version: 2.1
Name: phd-utils
Version: 0.1.13
Summary: A collection of utilities for PhD students
Author: Henrique Weber
